setup.py
django_restapi.egg-info/PKG-INFO
django_restapi.egg-info/SOURCES.txt
django_restapi.egg-info/dependency_links.txt
django_restapi.egg-info/requires.txt
django_restapi.egg-info/top_level.txt
restapi/__init__.py
restapi/admin.py
restapi/apis.py
restapi/apps.py
restapi/client.py
restapi/decorators.py
restapi/exceptions.py
restapi/log.py
restapi/models.py
restapi/tests.py
restapi/urls.py
restapi/views.py
restapi/management/__init__.py
restapi/management/commands/__init__.py
restapi/management/commands/testapi.py
restapi/migrations/__init__.py
restapi/templates/restapi/api.html
restapi/templates/restapi/doc.html